mastapy/__init__.py
mastapy/mastapy.py
mastapy/version.py
mastapy-1.0.16.dist-info/LICENSE
mastapy-1.0.16.dist-info/METADATA
mastapy-1.0.16.dist-info/WHEEL
mastapy-1.0.16.dist-info/top_level.txt
mastapy-1.0.16.dist-info/RECORD
