Metadata-Version: 2.1
Name: mastapy
Version: 1.0.16
Summary: A package for integrating scripts with Masta
Home-page: https://www.smartmt.com/cae-software/masta/overview/
Author: Connor Thornley
Author-email: connor.thornley@smartmt.com
License: UNKNOWN
Platform: UNKNOWN
Classifier: Programming Language :: Python :: 3
Classifier: License :: OSI Approved :: MIT License
Classifier: Operating System :: OS Independent
Requires-Dist: ptvsd (>=4.2)
Requires-Dist: pythonnet (>=2.4.0)
Requires-Dist: mkl
Requires-Dist: matplotlib
Requires-Dist: numpy
Requires-Dist: scipy
Requires-Dist: pandas
